Metadata-Version: 2.1
Name: confidenceinterval
Version: 1.0.2
Summary: Confidence Intervals in python
Home-page: https://github.com/jacobgil/confidenceinterval
Author: Jacob Gildenblat
Author-email: jacob.gildenblat@gmail.com
Project-URL: Bug Tracker, https://github.com/jacobgil/confidenceinterval/issues
Classifier: Programming Language :: Python :: 3
Classifier: License :: OSI Approved :: MIT License
Classifier: Operating System :: OS Independent
Requires-Python: >=3.6
License-File: LICENSE
